MANIFEST.in
README.md
setup.py
ChlClean/__init__.py
ChlClean/fasq_del.py
ChlClean/main.py
ChlClean/parse.py
ChlClean/remove_cloroplasts.py
ChlClean/ggenes/gg_chloroplasts.1.bt2
ChlClean/ggenes/gg_chloroplasts.2.bt2
ChlClean/ggenes/gg_chloroplasts.3.bt2
ChlClean/ggenes/gg_chloroplasts.4.bt2
ChlClean/ggenes/gg_chloroplasts.rev.1.bt2
ChlClean/ggenes/gg_chloroplasts.rev.2.bt2
chfilter.egg-info/PKG-INFO
chfilter.egg-info/SOURCES.txt
chfilter.egg-info/dependency_links.txt
chfilter.egg-info/entry_points.txt
chfilter.egg-info/requires.txt
chfilter.egg-info/top_level.txt