Metadata-Version: 1.1
Name: chfilter
Version: 1.3
Summary: Simple instructions to remove 16s rRNA reads from metagenomics samples
Home-page: https://github.com/gaarangoa/chfilter
Author: Gustavo Arango
Author-email: gustavo1@vt.edu
License: BSD-2
Keywords: metagenomics
Platform: UNKNOWN
Classifier: Development Status :: 4 - Beta
Classifier: Intended Audience :: Developers
Classifier: License :: OSI Approved :: BSD License
Classifier: Programming Language :: Python :: 2.7
Classifier: Programming Language :: Python :: 3
